jupyterlab_executor/__init__.py
jupyterlab_executor/_version.py
jupyterlab_executor-2023.1.1.data/data/share/jupyter/labextensions/@gavincyi/jupyterlab-executor/package.json
jupyterlab_executor-2023.1.1.data/data/share/jupyter/labextensions/@gavincyi/jupyterlab-executor/schemas/@gavincyi/jupyterlab-executor/executor.json
jupyterlab_executor-2023.1.1.data/data/share/jupyter/labextensions/@gavincyi/jupyterlab-executor/schemas/@gavincyi/jupyterlab-executor/package.json.orig
jupyterlab_executor-2023.1.1.data/data/share/jupyter/labextensions/@gavincyi/jupyterlab-executor/static/220.7cb15f9a879b6c1a8f3f.js
jupyterlab_executor-2023.1.1.data/data/share/jupyter/labextensions/@gavincyi/jupyterlab-executor/static/520.1e50fa6ca2ce22366297.js
jupyterlab_executor-2023.1.1.data/data/share/jupyter/labextensions/@gavincyi/jupyterlab-executor/static/747.49a0a14454f1cd5d6704.js
jupyterlab_executor-2023.1.1.data/data/share/jupyter/labextensions/@gavincyi/jupyterlab-executor/static/remoteEntry.72532ab7d6149d66bf3d.js
jupyterlab_executor-2023.1.1.data/data/share/jupyter/labextensions/@gavincyi/jupyterlab-executor/static/style.js
jupyterlab_executor-2023.1.1.data/data/share/jupyter/labextensions/@gavincyi/jupyterlab-executor/static/third-party-licenses.json
jupyterlab_executor-2023.1.1.data/data/share/jupyter/labextensions/@gavincyi/jupyterlab-executor/install.json
jupyterlab_executor-2023.1.1.dist-info/METADATA
jupyterlab_executor-2023.1.1.dist-info/WHEEL
jupyterlab_executor-2023.1.1.dist-info/licenses/LICENSE
jupyterlab_executor-2023.1.1.dist-info/RECORD
