Metadata-Version: 2.1
Name: jupyterlab_executor
Version: 2023.1.1
Summary: JupyterLab extension of executing the scripts
Project-URL: Homepage, https://github.com/gavincyi/jupyterlab-executor
Project-URL: Bug Tracker, https://github.com/gavincyi/jupyterlab-executor/issues
Project-URL: Repository, https://github.com/gavincyi/jupyterlab-executor.git
Author-email: Gavin Chan <gavincyi@gmail.com>
License: BSD 3-Clause License
License-File: LICENSE
Classifier: Framework :: Jupyter
Classifier: Framework :: Jupyter :: JupyterLab
Classifier: Framework :: Jupyter :: JupyterLab :: 4
Classifier: Framework :: Jupyter :: JupyterLab :: Extensions
Classifier: Framework :: Jupyter :: JupyterLab :: Extensions :: Prebuilt
Classifier: License :: OSI Approved :: BSD License
Classifier: Programming Language :: Python
Classifier: Programming Language :: Python :: 3
Classifier: Programming Language :: Python :: 3.8
Classifier: Programming Language :: Python :: 3.9
Classifier: Programming Language :: Python :: 3.10
Classifier: Programming Language :: Python :: 3.11
Requires-Python: >=3.8
